ou/__init__.py
ou-0.0.5.dist-info/licenses/LICENSE
ou-0.0.5.dist-info/METADATA
ou-0.0.5.dist-info/WHEEL
ou-0.0.5.dist-info/top_level.txt
ou-0.0.5.dist-info/RECORD
