Metadata-Version: 2.4
Name: ou
Version: 0.0.5
Summary: Window pairs of sequences
Home-page: https://github.com/t-c-w/ou
Author: Thor Whalen
License: apache-2.0
Platform: any
License-File: LICENSE
Dynamic: license-file
